{"cameraMode":{"drawMode":0,"name":"Shaded","section":"Shading Mode"},"sceneLighting":true,"audioPlay":false,"sceneViewState":{"showFog":true,"showMaterialUpdate":false,"showSkybox":true,"showFlares":true,"showImageEffects":true,"showParticleSystems":true},"in2DMode":false,"pivot":{"x":-0.21299123764038087,"y":1.8058897256851197,"z":0.6520113945007324},"rotation":{"x":0.03749457746744156,"y":0.44882869720458987,"z":-0.018986918032169343,"w":0.8928214311599731},"size":5.946279525756836,"orthographic":false}